pytest_testrail_plugin/__init__.py
pytest_testrail_plugin/conftest.py
pytest_testrail_plugin/plugin.py
pytest_testrail_plugin/testrail_api.py
pytest_testrail_plugin-0.0.3.dist-info/METADATA
pytest_testrail_plugin-0.0.3.dist-info/WHEEL
pytest_testrail_plugin-0.0.3.dist-info/entry_points.txt
pytest_testrail_plugin-0.0.3.dist-info/top_level.txt
pytest_testrail_plugin-0.0.3.dist-info/RECORD
