Metadata-Version: 2.1
Name: pytest-testrail-plugin
Version: 0.0.3
Summary: PyTest plugin for TestRail
Home-page: https://git.cashwagon.com/billing/pytest-testrail-plugin
Author: Max Ponomarev
Author-email: maxim.ponomarev@cashwagon.com
License: BSD
Platform: UNKNOWN
Classifier: Development Status :: 3 - Alpha
Classifier: Environment :: Web Environment
Classifier: Intended Audience :: Developers
Classifier: License :: OSI Approved :: BSD License
Classifier: Operating System :: OS Independent
Classifier: Topic :: Internet :: WWW/HTTP
Classifier: Programming Language :: Python :: 3.7
Requires-Python: >=3.7
Requires-Dist: pytest
Requires-Dist: requests (<3,>=2.20.0)
Requires-Dist: PyYAML (<6,>=5.3)
